Workbook

Sheet Info
C7: File name | D7: FTT-Tr-25x61_2020.xlsx
C8: Author | D8: Cambridge Econometrics
C10: Version | D10: 1.2
C11: Last revised | D11: 43893
C12: Status | D12: Under development
C13: Source | D13: J:\Projects\....
C15: Purpose | D15: This excel file contains all cost data, assumptions and policy levers related to the FTT road transport model. A python job will be developed to read in the data from these sheets and to store it in the appropriate databanks.
C19: Sheets in this file:
D21: Info | F21: This documentation sheet
D22: Titles | F22: All titles used in FTT:Tr
D23: TEWS | F23: Historical market shares of vehicles (1990 to 2100)
D24: BTTC | F24: Cost matrices
D25: Assumptions | F25: Contains data for the following variables: TEWA, TEWB, TESF, TESH, TSFD, TETH, and TEWW
D26: RFLT# | F26: Car stock, history and projection. Scenario dependent, i.e. # = 0 to 9. Use this in case exogenous projections of car stocks are preferred over endogenous calculation.
D27: RVKM# | F27: Demand for driving projections. Scenario dependent, i.e. # = 0 to 9. Use this in case exogenous projections of driving demand is preferred over endogenous calculation.
D28: RTKM# | F28: Demand for freight transport. Scenario dependent, i.e. # = 0 to 9. Only exogenous.
D29: RTFT# | F29: Fuel tax. Scenario dependent, i.e. # = 0 to 9. Policy lever.
D30: RBFM# | F30: Biofuel blending mandate. Scenario dependent, i.e. # = 0 to 9. Policy lever.
D31: RHSM# | F31: Hydrogen fuel substition for freight transport. Scenario dependent, i.e. # = 0 to 9. Exogenous assumption.
D32: RTCO# | F32: Registration tax. Scenario dependent, i.e. # = 0 to 9. Policy lever.
... D36: TWSA# | F36: Exogenous market share changes. Scenario dependent, i.e. # = 0 to 9. Policy lever.
B39: History and authorisation table
C41: Version | D41: Release date | E41: Released by | F41: Description
C43: 1.2
C44: 1.1
C45: 1 | D45: 43893 | E45: PV | F45: Setting up FTT:Tr template to survive the test of time.

Sheet Titles
A1: # | C1: # | D1: C5TI | E1: Units | F1: # | G1: C2TI
A2: 1 | B2: DAC | C2: 1 | D2: Investment | E2: (£/tCO2 or £/kgH2) | F2: 1
A3: 2 | B3: DOC | C3: =C2+1 -> 2 | D3: std | E3: (£/tCO2 or £/kgH2) | F3: 2
A4: 3 | B4: Electrolyser | C4: =C3+1 -> 3 | D4: O&M (fixed) | E4: (£/tCO2 or £/kgH2) | F4: 3
A5: 4 | B5: Methanation | C5: =C4+1 -> 4 | D5: std | E5: (£/tCO2 or £/kgH2) | F5: 4
C6: =C5+1 -> 5 | D6: O&M (variable) | F6: 5
C7: =C6+1 -> 6 | D7: std | F7: 6
C8: =C7+1 -> 7 | D8: Lifetime | E8: (years) | F8: 7
C9: =C8+1 -> 8 | D9: Lead time | E9: (MWh/tCO2 or MWh/kgH2) | F9: 8
C10: =C9+1 -> 9 | D10: Efficiency | F10: 9
C11: =C10+1 -> 10 | D11: Capacity factor | E11: (tCO2/yr or kgH2/yr) | F11: 10
C12: =C11+1 -> 11 | D12: Baseline capacity | E12: (tCO2/h or kgH2/h) | F12: 11
C13: =C12+1 -> 12 | D13: Capture/production rates | F13: 12
C14: =C13+1 -> 13 | D14: Eff learning | F14: 13
C15: =C14+1 -> 14 | D15: Inv learning | F15: 14
C16: =C15+1 -> 15 | D16: OPEX learning | F16: 15
F17: 16
F18: 17
F19: 18
F20: 19
F21: 20
F22: 21
F23: 22
F24: 23
F25: 24
F26: 25

Sheet GCET
A1: 0 | B1: 0 | C1: 0 | D1: 0 | E1: 0 | F1: 0 | G1: 0 | H1: 0 | I1: 0 | J1: 0 | K1: 0 | L1: 0
A2: 0 | B2: The costs are in 20xx GBP
A3: 0 | B3: This cost data uses a combination of data from
A4: 0 | C4: 1 | D4: 2 | E4: 3 | F4: 4 | G4: 5 | H4: 6 | I4: 7 | J4: 8 | K4: 9 | L4: 10 | M4: 11 | N4: 12 | O4: 13 | P4: 14 | Q4: 15
A5: 1 | C5: =Titles!$D$2 -> Investment | D5: =Titles!$D$3 -> std | E5: =Titles!$D$4 -> O&M (fixed) | F5: =Titles!$D$5 -> std | G5: =Titles!$D$6 -> O&M (variable) | H5: =Titles!$D$7 -> std | I5: =Titles!$D$8 -> Lifetime | J5: =Titles!$D9 -> Lead time | K5: =Titles!$D10 -> Efficiency | L5: =Titles!$D11 -> Capacity factor | M5: =Titles!$D12 -> Baseline capacity | N5: =Titles!$D13 -> Capture/production rates | O5: =Titles!$D14 -> Eff learning | P5: =Titles!$D15 -> Inv learning | Q5: =Titles!$D16 -> OPEX learning
B6: =Titles!$B$2 -> DAC | I6: 20 | K6: 4.01 | L6: 0.9 | O6: -0.05 | P6: -0.12 | Q6: -0.075
B7: =Titles!$B$3 -> DOC | I7: 15 | K7: 7.2 | L7: 0.9
B8: =Titles!$B$4 -> Electrolyser | I8: 8 | K8: 50 | L8: 0.9 | O8: -0.02 | P8: -0.18 | Q8: -0.18
B9: =Titles!$B$5 -> Methanation | L9: 0.9

Sheet GMP
A1: 0 | B1: 0 | C1: 0 | D1: 0 | E1: 0 | F1: 0 | G1: 0 | H1: 0 | I1: 0 | J1: 0 | K1: 0 | L1: 0 | M1: 0 | N1: 0 | O1: 0 | P1: 0 | Q1: 0 | R1: 0 | S1: 0 | T1: 0 | U1: 0 | V1: 0 | W1: 0 | X1: 0 | Y1: 0 | Z1: 0 | AA1: 0 | AB1: 0 | AC1: 0 | AD1: 0 | AE1: 0 | AF1: 0 | AG1: 0 | AH1: 0 | AI1: 0 | AJ1: 0 | AK1: 0 | AL1: 0 | AM1: 0 | AN1: 0 | AO1: 0 | AP1: 0 | AQ1: 0 | AR1: 0 | AS1: 0 | AT1: 0 | AU1: 0 | AV1: 0 | AW1: 0 | AX1: 0 | AY1: 0 | AZ1: 0 | BA1: 0 | BB1: 0 | BC1: 0 | BD1: 0 | BE1: 0 | BF1: 0 | BG1: 0 | BH1: 0 | BI1: 0 | BJ1: 0 | BK1: 0 | BL1: 0 | BM1: 0 | BN1: 0 | BO1: 0 | BP1: 0 | BQ1: 0 | BR1: 0 | BS1: 0 | BT1: 0 | BU1: 0 | BV1: 0 | BW1: 0 | BX1: 0 | BY1: 0 | BZ1: 0 | CA1: 0 | CB1: 0 | CC1: 0 | CD1: 0 | CE1: 0 | CF1: 0 | CG1: 0 | CH1: 0 | CI1: 0 | CJ1: 0 | CK1: 0 | CL1: 0 | CM1: 0 | CN1: 0 | CO1: 0 | CP1: 0 | CQ1: 0 | CR1: 0 | CS1: 0 | CT1: 0 | CU1: 0 | CV1: 0 | CW1: 0 | CX1: 0 | CY1: 0 | CZ1: 0 | DA1: 0 | DB1: 0 | DC1: 0 | DD1: 0 | DE1: 0 | DF1: 0 | DG1: 0 | DH1: 0 | DI1: 0
A2: 0
A3: 0
A4: 0
A5: 1 | C5: 1990 | D5: 1991 | E5: 1992 | F5: 1993 | G5: 1994 | H5: 1995 | I5: 1996 | J5: 1997 | K5: 1998 | L5: 1999 | M5: 2000 | N5: 2001 | O5: 2002 | P5: 2003 | Q5: 2004 | R5: 2005 | S5: 2006 | T5: 2007 | U5: 2008 | V5: 2009 | W5: 2010 | X5: 2011 | Y5: 2012 | Z5: 2013 | AA5: 2014 | AB5: 2015 | AC5: 2016 | AD5: 2017 | AE5: 2018 | AF5: 2019 | AG5: 2020 | AH5: 2021 | AI5: 2022 | AJ5: 2023 | AK5: 2024 | AL5: 2025 | AM5: 2026 | AN5: 2027 | AO5: 2028 | AP5: 2029 | AQ5: 2030 | AR5: 2031 | AS5: 2032 | AT5: 2033 | AU5: 2034 | AV5: 2035 | AW5: 2036 | AX5: 2037 | AY5: 2038 | AZ5: 2039 | BA5: 2040 | BB5: 2041 | BC5: 2042 | BD5: 2043 | BE5: 2044 | BF5: 2045 | BG5: 2046 | BH5: 2047 | BI5: 2048 | BJ5: 2049 | BK5: 2050 | BL5: 2051 | BM5: 2052 | BN5: 2053 | BO5: 2054 | BP5: 2055 | BQ5: 2056 | BR5: 2057 | BS5: 2058 | BT5: 2059 | BU5: 2060 | BV5: 2061 | BW5: 2062 | BX5: 2063 | BY5: 2064 | BZ5: 2065 | CA5: 2066 | CB5: 2067 | CC5: 2068 | CD5: 2069 | CE5: 2070 | CF5: 2071 | CG5: 2072 | CH5: 2073 | CI5: 2074 | CJ5: 2075 | CK5: 2076 | CL5: 2077 | CM5: 2078 | CN5: 2079 | CO5: 2080 | CP5: 2081 | CQ5: 2082 | CR5: 2083 | CS5: 2084 | CT5: 2085 | CU5: 2086 | CV5: 2087 | CW5: 2088 | CX5: 2089 | CY5: 2090 | CZ5: 2091 | DA5: 2092 | DB5: 2093 | DC5: 2094 | DD5: 2095 | DE5: 2096 | DF5: 2097 | DG5: 2098 | DH5: 2099 | DI5: 2100
